LICENSE
README.md
pyproject.toml
setup.py
damenltk/installing-nltk-modules.py
damenltk/runtests.sh
damenltk.egg-info/PKG-INFO
damenltk.egg-info/SOURCES.txt
damenltk.egg-info/dependency_links.txt
damenltk.egg-info/entry_points.txt
damenltk.egg-info/namespace_packages.txt
damenltk.egg-info/not-zip-safe
damenltk.egg-info/requires.txt
damenltk.egg-info/top_level.txt
damenltk/src/__init__.py
damenltk/src/damenltk.py
damenltk/src/stopwords.py
damenltk/src/syllable.py
damenltk/test/__init__.py
damenltk/test/test_bernoulli.py
damenltk/test/test_corpus.py
damenltk/test/test_damenltk.py
damenltk/test/test_gender.py
damenltk/test/test_gutenberg.py
damenltk/test/test_maxent.py
damenltk/test/test_semantic_tree.py
damenltk/test/test_sentence_similarity.py
damenltk/test/test_sentiment.py
damenltk/test/test_stem.py
damenltk/test/test_stopwords.py
damenltk/test/test_svc.py
damenltk/test/test_syn.py
damenltk/test/test_tokenize.py
damenltk/test/test_wordnet.py